az_k8s_operations/__init__.py
az_k8s_operations/azdevops.py
az_k8s_operations/common.py
az_k8s_operations/k8s.py
az_k8s_operations/maintenance.py
az_k8s_operations/report.py
az_k8s_operations/spn.py
package/__init__.py
package/setup.py
package/az_k8s_operations/__init__.py
package/az_k8s_operations/azdevops.py
package/az_k8s_operations/common.py
package/az_k8s_operations/k8s.py
package/az_k8s_operations/maintenance.py
package/az_k8s_operations/report.py
package/az_k8s_operations/spn.py
az_k8s_operations-1.1.24.dist-info/LICENSE
az_k8s_operations-1.1.24.dist-info/METADATA
az_k8s_operations-1.1.24.dist-info/WHEEL
az_k8s_operations-1.1.24.dist-info/top_level.txt
az_k8s_operations-1.1.24.dist-info/RECORD
